openbank_testkit/__init__.py
openbank_testkit/http.py
openbank_testkit/package.py
openbank_testkit/platform.py
openbank_testkit/shell.py
openbank_testkit/ssl.py
openbank_testkit/statsd.py
openbank_testkit-0.64.dist-info/METADATA
openbank_testkit-0.64.dist-info/WHEEL
openbank_testkit-0.64.dist-info/top_level.txt
openbank_testkit-0.64.dist-info/RECORD
