Metadata-Version: 2.1
Name: openbank-testkit
Version: 0.64
Summary: openbank testkit libraries
Home-page: https://github.com/jancajthaml-openbank/testkit
Author: jan.cajthaml
Author-email: jan.cajthaml@gmail.com
License: Apache 2.0
Platform: UNKNOWN
